.gitignore
LICENSE
README
README.md
__init__.py
afitter.py
cleaner.py
kmodels.py
setup.cfg
setup.py
afgui/__init__.py
afgui/db.sqlite3
afgui/example1.csv
afgui/example2.csv
afgui/example3.csv
afgui/manage.py
afgui/tfitter.py
afgui/afgui/LICENSE
afgui/afgui/__init__.py
afgui/afgui/settings.py
afgui/afgui/settings_for_servers.py
afgui/afgui/urls.py
afgui/afgui/views.py
afgui/afgui/wsgi.py
afgui/fitter/__init__.py
afgui/fitter/admin.py
afgui/fitter/apps.py
afgui/fitter/fbackend.py
afgui/fitter/forms.py
afgui/fitter/models.py
afgui/fitter/tests.py
afgui/fitter/urls.py
afgui/fitter/views.py
afgui/fitter/migrations/0001_initial.py
afgui/fitter/migrations/0002_kfitssession_kinetic_params.py
afgui/fitter/migrations/__init__.py
afgui/fitter/templates/upload.htm
afgui/fitter/templates/fitter/get.htm
afgui/fitter/templates/fitter/get_nosid.htm
afgui/fitter/templates/fitter/index.htm
afgui/fitter/templates/fitter/test.htm
afgui/fitter/templates/fitter/bootstrap/FigS1.png
afgui/fitter/templates/fitter/bootstrap/LICENSE
afgui/fitter/templates/fitter/bootstrap/orimon.css
afgui/fitter/templates/fitter/bootstrap/theme.css
afgui/fitter/templates/fitter/bootstrap/assets/brand/bootstrap-outline.svg
afgui/fitter/templates/fitter/bootstrap/assets/brand/bootstrap-punchout.svg
afgui/fitter/templates/fitter/bootstrap/assets/brand/bootstrap-solid.svg
afgui/fitter/templates/fitter/bootstrap/assets/css/docs.min.css
afgui/fitter/templates/fitter/bootstrap/assets/css/docs.min.css.map
afgui/fitter/templates/fitter/bootstrap/assets/css/ie10-viewport-bug-workaround.css
afgui/fitter/templates/fitter/bootstrap/assets/css/src/docs.css
afgui/fitter/templates/fitter/bootstrap/assets/css/src/pygments-manni.css
afgui/fitter/templates/fitter/bootstrap/assets/flash/ZeroClipboard.swf
afgui/fitter/templates/fitter/bootstrap/assets/img/components.png
afgui/fitter/templates/fitter/bootstrap/assets/img/devices.png
afgui/fitter/templates/fitter/bootstrap/assets/js/customize.min.js
kfits.egg-info/PKG-INFO
kfits.egg-info/SOURCES.txt
kfits.egg-info/dependency_links.txt
kfits.egg-info/entry_points.txt
kfits.egg-info/requires.txt
kfits.egg-info/top_level.txt