Metadata-Version: 1.0
Name: kfits
Version: 1.2.4
Summary: Kinetics Fitting Software
Home-page: https://github.com/odedrim/kfits
Author: Oded Rimon
Author-email: oded.rimon@mail.huji.ac.il
License: UNKNOWN
Platform: UNKNOWN
